nuregi/__init__.py
nuregi/api.py
nuregi/exceptions.py
nuregi/scraper.py
nuregi-0.3.0.dist-info/LICENSE.txt
nuregi-0.3.0.dist-info/METADATA
nuregi-0.3.0.dist-info/WHEEL
nuregi-0.3.0.dist-info/RECORD
