Metadata-Version: 2.1
Name: nuregi
Version: 0.3.0
Summary: A basic Python-based API client library for registrar.nu.edu.kz
Home-page: https://github.com/aldan/nuregi
License: GPL-3.0-only
Author: aldan
Author-email: gitaldan@gmail.com
Requires-Python: >=3.11,<4.0
Classifier: Development Status :: 4 - Beta
Classifier: Intended Audience :: Developers
Classifier: License :: OSI Approved :: GNU General Public License v3 (GPLv3)
Classifier: Programming Language :: Python :: 3
Classifier: Programming Language :: Python :: 3.11
Classifier: Topic :: Software Development :: Libraries :: Python Modules
Requires-Dist: jpype1 (>=1.4.1,<2.0.0)
Requires-Dist: pandas (>=2.1.3,<3.0.0)
Requires-Dist: requests (>=2.31.0,<3.0.0)
Requires-Dist: tabula-py (>=2.9.0,<3.0.0)
Project-URL: Bug Tracker, https://github.com/aldan/nuregi/issues
Project-URL: Repository, https://github.com/aldan/nuregi
